rag2f_openai_embedder/__init__.py
rag2f_openai_embedder/_version.py
rag2f_openai_embedder/embedder.py
rag2f_openai_embedder/plugin_context.py
rag2f_openai_embedder/plugin_overrides.py
rag2f_openai_embedder-0.0.1.dist-info/licenses/LICENSE
rag2f_openai_embedder-0.0.1.dist-info/METADATA
rag2f_openai_embedder-0.0.1.dist-info/WHEEL
rag2f_openai_embedder-0.0.1.dist-info/entry_points.txt
rag2f_openai_embedder-0.0.1.dist-info/top_level.txt
rag2f_openai_embedder-0.0.1.dist-info/RECORD
