Metadata-Version: 2.4
Name: rag2f-openai-embedder
Version: 0.0.1
Summary: OpenAI Embedder Plugin for RAG2F
Author-email: Dario Chini <dariochini@gmail.com>
License: GPL-3.0
Project-URL: Homepage, https://github.com/rag2f/rag2f
Project-URL: Repository, https://github.com/rag2f
Classifier: License :: OSI Approved :: GNU General Public License v3 (GPLv3)
Classifier: Programming Language :: Python :: 3.12
Requires-Python: >=3.12
License-File: LICENSE
Requires-Dist: rag2f<0.6,>=0.0
Requires-Dist: openai==2.8.0
Provides-Extra: dev
Requires-Dist: pre-commit==4.5.1; extra == "dev"
Requires-Dist: ruff==0.14.11; extra == "dev"
Requires-Dist: pytest; extra == "dev"
Requires-Dist: pytest-asyncio; extra == "dev"
Requires-Dist: rich; extra == "dev"
Requires-Dist: pytest-rich; extra == "dev"
Requires-Dist: pytest-icdiff; extra == "dev"
Requires-Dist: pytest-clarity; extra == "dev"
Requires-Dist: pytest-instafail; extra == "dev"
Requires-Dist: coverage; extra == "dev"
Requires-Dist: pytest-cov; extra == "dev"
Requires-Dist: respx; extra == "dev"
Dynamic: license-file
